{
	"name": "刀豆",
	"jieshao": {
		"title": "刀豆的介绍",
		"content": "\n      刀豆属于豆科，因豆荚形似刀而得名“刀豆”。又因荚形似人挟剑横斜，故又名“挟剑豆”。主要品种有蔓性、矮性两种。蔓性刀豆，亦称“大刀豆”、“中国刀豆”、“关刀豆”、“马刀豆”、“刀鞘豆”、“刀巴豆”。一年生草本，茎蔓生，复叶，小叶3片，自叶腋抽生花轴，其上开较大的蝶形花数朵，花紫红色。结大而扁的荚果，长25～30厘米，宽约3．5厘米。种子大有10～14粒，肾脏形，红色或褐色。原产东半球热带地区。矮性刀豆，亦称“矮刀豆”、“立刀豆”、“洋刀豆”。茎矮生或半蔓生，花紫色，荚果较蔓性刀豆小，种子白色，原产印度。\n    \n"
	},
	"foodvalue": {
		"title": "刀豆的营养成分(营养素含量/每100克)",
		"data": [
			{
				"name": "食部",
				"value": "92%"
			},
			{
				"name": "水分(克)",
				"value": "89"
			},
			{
				"name": "能量(千卡)",
				"value": "40"
			},
			{
				"name": "蛋白质(克)",
				"value": "3.1"
			},
			{
				"name": "脂肪(克)",
				"value": "0.3"
			},
			{
				"name": "碳水化合物(克)",
				"value": "7"
			},
			{
				"name": "不溶性纤维(克)",
				"value": "1.8"
			},
			{
				"name": "胆固醇(毫克)",
				"value": " — "
			},
			{
				"name": "灰分(克)",
				"value": "0.6"
			},
			{
				"name": "维生素A(微克RE)",
				"value": "37"
			},
			{
				"name": "胡萝卜素(微克)",
				"value": "220"
			},
			{
				"name": "视黄醇(微克)",
				"value": " — "
			},
			{
				"name": "硫胺素(毫克)",
				"value": "0.05"
			},
			{
				"name": "核黄素(毫克)",
				"value": "0.07"
			},
			{
				"name": "尼克酸(毫克)",
				"value": "1"
			},
			{
				"name": "维生素C(毫克)",
				"value": "15"
			},
			{
				"name": "维生素E(毫克)",
				"value": "0.4"
			},
			{
				"name": "钙(毫克)",
				"value": "49"
			},
			{
				"name": "磷(毫克)",
				"value": "57"
			},
			{
				"name": "钾(毫克)",
				"value": "209"
			},
			{
				"name": "钠(毫克)",
				"value": "8.5"
			},
			{
				"name": "镁(毫克)",
				"value": "29"
			},
			{
				"name": "铁(毫克)",
				"value": "4.6"
			},
			{
				"name": "锌(毫克)",
				"value": "0.84"
			},
			{
				"name": "硒(微克)",
				"value": "0.88"
			},
			{
				"name": "铜(毫克)",
				"value": "0.09"
			},
			{
				"name": "锰(毫克)",
				"value": "0.45"
			},
			{
				"name": "酒精(毫升)%",
				"value": " — "
			},
			{
				"name": "酒精(克)",
				"value": " — "
			},
			{
				"name": "",
				"value": ""
			},
			{
				"name": "",
				"value": ""
			},
			{
				"name": "",
				"value": ""
			}
		]
	},
	"gongxiao": {
		"title": "刀豆的",
		"content": ""
	},
	"yingyangjiazhi": {
		"title": "刀豆的营养价值",
		"content": "\n刀豆含有尿毒酶、血细胞凝集素、刀豆氨酸等；近年来，又在嫩荚中发现刀豆赤霉I和Ⅱ等，有治疗肝性昏迷和抗癌的作用。      \n"
	},
	"shiyongxiaoguo": {
		"title": "刀豆的使用效果",
		"content": "\n刀豆性平、味甘；\n具有温中下气、利肠胃、止呕逆、益肾补元的功效；\n对于肾虚腰痛、气滞呃逆、风温腰痛、小儿疝气等症有一定疗效。\n刀豆对人体镇静也有很好的作用，可以增强大脑皮质的抑制过程，使神志清晰，精力充沛。\n"
	},
	"shiyongrenqun": {
		"title": "刀豆的适用人群",
		"content": "\n一般人群均可食用，尤适于肾虚腰痛、气滞呃逆、风温腰痛、小儿疝气等症患者食用。\n"
	}
}
