{
	"name": "挂面",
	"jieshao": {
		"title": "面条的介绍",
		"content": "面条俗称“面”、“水面”、“面条子”；古称“汤饼”、“奢面”、“素饼”、“煮饼”、“水引饼”、“不托”等；面条一词是后来才有的；据考证，我国面条起源于汉代，至今已有2000多年的历史，因面条要在“汤”中煮熟，所以又叫“汤饼”。早期的面条有片状的、条状的。片状的是将面团托在手上，拉扯成面片下锅而成。到了魏、晋、南北朝，面条的种类增多。"
	},
	"foodvalue": {
		"title": "面条的营养成分(营养素含量/每100克)",
		"data": [
			{
				"name": "食部",
				"value": "100%"
			},
			{
				"name": "水分(克)",
				"value": "28.5"
			},
			{
				"name": "能量(千卡)",
				"value": "286"
			},
			{
				"name": "蛋白质(克)",
				"value": "8.3"
			},
			{
				"name": "脂肪(克)",
				"value": "0.7"
			},
			{
				"name": "碳水化合物(克)",
				"value": "61.9"
			},
			{
				"name": "不溶性纤维(克)",
				"value": "0.8"
			},
			{
				"name": "胆固醇(毫克)",
				"value": " — "
			},
			{
				"name": "灰分(克)",
				"value": "0.6"
			},
			{
				"name": "维生素A(微克RE)",
				"value": " — "
			},
			{
				"name": "胡萝卜素(微克)",
				"value": " — "
			},
			{
				"name": "视黄醇(微克)",
				"value": " — "
			},
			{
				"name": "硫胺素(毫克)",
				"value": "0.22"
			},
			{
				"name": "核黄素(毫克)",
				"value": "0.07"
			},
			{
				"name": "尼克酸(毫克)",
				"value": "1.4"
			},
			{
				"name": "维生素C(毫克)",
				"value": " — "
			},
			{
				"name": "维生素E(毫克)",
				"value": "0.59"
			},
			{
				"name": "钙(毫克)",
				"value": "11"
			},
			{
				"name": "磷(毫克)",
				"value": "162"
			},
			{
				"name": "钾(毫克)",
				"value": "135"
			},
			{
				"name": "钠(毫克)",
				"value": "28"
			},
			{
				"name": "镁(毫克)",
				"value": "39"
			},
			{
				"name": "铁(毫克)",
				"value": "3.6"
			},
			{
				"name": "锌(毫克)",
				"value": "1.43"
			},
			{
				"name": "硒(微克)",
				"value": "11.74"
			},
			{
				"name": "铜(毫克)",
				"value": "0.17"
			},
			{
				"name": "锰(毫克)",
				"value": "0.86"
			},
			{
				"name": "酒精(毫升)%",
				"value": " — "
			},
			{
				"name": "酒精(克)",
				"value": " — "
			},
			{
				"name": "",
				"value": ""
			},
			{
				"name": "",
				"value": ""
			},
			{
				"name": "",
				"value": ""
			}
		]
	},
	"gongxiao": {
		"title": "面条的功效",
		"content": "\n1.养胃,吃碗温热的面条最有利于营养吸收; \n2.增强免疫力,口感筋道的面条所含的蛋白质更多，能补充人体所需的营养。蛋白质是维持免疫机能最重要的营养素，为构成白血球和抗体的主要成份; \n3.改善贫血,促进人体气血运行; \n4.易于消化吸收,经过煮沸的面条最为洁净，可以大大减少肠胃疾病的发生，因此面条成为中国最常见的食品之一。\n"
	},
	"yingyangjiazhi": {
		"title": "面条的营养价值",
		"content": "面条的主要营养成分有蛋白质、脂肪、碳水化合物等；面条易于消化吸收，有改善贫血、增强免疫力、平衡营养吸收等功效。"
	},
	"shiyongxiaoguo": {
		"title": "面条的使用效果",
		"content": "\n1. 新鲜切面不宜存放时间过长，以免营养成分受损。\n2. 买来的切面有时碱味很重，在面条快煮好的时候，加入几滴醋，可以使面条碱味全消，面条的颜色也会由黄变白。\n3. 就品种来说，常吃的有汤面条，捞面条、卤面条、炒面条、炯面条、蒸面条、烩面条、拉面条等。从形状上说，有一厘米宽的宽面、窄如韭叶的窄面、细如发丝的龙须面，也有菱形的面叶儿、绵长不规则的面片等。从味道上说，有淡味、咸味、辣味、酸味等。\n"
	},
	"shiyongrenqun": {
		"title": "面条的适用人群",
		"content": "\n一般人皆可食用。\n"
	}
}
