{
	"name": "海苔",
	"jieshao": {
		"title": "海苔的介绍",
		"content": "\n海苔就是紫菜；但是紫菜不全是海苔。紫菜烤熟之后质地脆嫩，入口即化，特别是经过调味处理之后，添加了油脂、盐和其他调料，就摇身变成了特别美味的“海苔”了。海苔浓缩了紫菜当中的各种B族维生素，特别是核黄素和尼克酸的含量十分丰富，还有不少维生素A和维生素E，以及少量的维生素C。海苔中含有15%左右的矿物质，其中有维持正常生理功能所必需的钾、钙、镁、磷、铁、锌、铜、锰等，其中含硒和碘尤其丰富，这些矿物质可以帮助人体维持机体的酸碱平衡，有利于儿童的生长发育，对老年人延缓衰老也有帮助。\n"
	},
	"foodvalue": {
		"title": "海苔的营养成分(营养素含量/每100克)",
		"data": [
			{
				"name": "营养素",
				"value": "含量(每100克)"
			},
			{
				"name": "热量(大卡)",
				"value": "177.00"
			},
			{
				"name": "碳水化合物(克)",
				"value": "50.40"
			},
			{
				"name": "脂肪(克)",
				"value": "4.80"
			},
			{
				"name": "蛋白质(克)",
				"value": "29.40"
			},
			{
				"name": "纤维素(克)",
				"value": "46.40"
			},
			{
				"name": "维生素A(微克)",
				"value": "一"
			},
			{
				"name": "维生素C(毫克)",
				"value": "一"
			},
			{
				"name": "维生素E(毫克)",
				"value": "一"
			},
			{
				"name": "胡罗卜素(微克)",
				"value": "一"
			},
			{
				"name": "硫胺素(毫克)",
				"value": "一"
			},
			{
				"name": "核黄素(毫克)",
				"value": "一"
			},
			{
				"name": "烟酸(毫克)",
				"value": "一"
			},
			{
				"name": "胆固醇(毫克)",
				"value": "一"
			},
			{
				"name": "镁(毫克)",
				"value": "一"
			},
			{
				"name": "钙(毫克)",
				"value": "一"
			},
			{
				"name": "铁(毫克)",
				"value": "一"
			},
			{
				"name": "锌(毫克)",
				"value": "一"
			},
			{
				"name": "铜(毫克)",
				"value": "一"
			},
			{
				"name": "锰(毫克)",
				"value": "一"
			},
			{
				"name": "钾(毫克)",
				"value": "一"
			},
			{
				"name": "磷(毫克)",
				"value": "一"
			},
			{
				"name": "钠(毫克)",
				"value": "一"
			},
			{
				"name": "硒(微克)",
				"value": "一"
			},
			{
				"name": "",
				"value": ""
			},
			{
				"name": "",
				"value": ""
			}
		]
	},
	"gongxiao": {
		"title": "海苔的功效",
		"content": "\n维持机体酸碱平衡，有利于生长发育，延缓衰老\n"
	},
	"yingyangjiazhi": {
		"title": "海苔的营养价值",
		"content": "\n1.海苔中所含藻胆蛋白具有降血糖、抗肿瘤的应用前景，其中的多糖具有抗衰老、降血脂、抗肿瘤等多方面的生物活性。海苔中所含的藻朊酸，还有助于清除人体内带毒性的金属，如锶和镉等。医疗人员还从海苔中开发出具有独特活性的海洋药物和保健食品，能有效预防神经老化，调节机体的新陈代谢。此外，海苔能预防和治疗消化性溃疡，延缓衰老，帮助女士保持皮肤的润滑健康。民间还有常让产后的妇女吃些紫菜的偏方，据说有明显的催乳效果。还有减肥的作用 。\n2.海苔浓缩了紫菜当中的各种B族维生素，特别是核黄素和尼克酸的含量十分丰富，还有不少维生素A和维生素E，以及少量的维生素C。海苔中含有15%左右的矿物质，其中有维持正常生理功能所必需的钾、钙、镁、磷、铁、锌、铜、锰等，其中含硒和碘尤其丰富，这些矿物质可以帮助人体维持机体的酸碱平衡，有利于儿童的生长发育，对老年人延缓衰老也有帮助。\n"
	},
	"shiyongxiaoguo": {
		"title": "海苔的使用效果",
		"content": "海苔的好处不仅在营养方面，它的保健效果更令人称道。英国研究人员在上世纪90年代就发现海苔可杀死癌细胞，增强免疫力。海苔中所含藻胆蛋白具有降血糖、抗肿瘤的应用前景，其中的多糖具有抗衰老、降血脂、抗肿瘤等多方面的生物活性。海苔中所含的藻朊酸，还有助于清除人体内带毒性的金属，如锶和镉等。医疗人员还从海苔中开发出具有独特活性的海洋药物和保健食品，能有效预防神经老化，调节机体的新陈代谢。此外，海苔能预防和治疗消化性溃疡，延缓衰老，帮助女士保持皮肤的润滑健康。民间还有常让产后的妇女吃些紫菜的偏方，据说有明显的催乳效果。"
	},
	"shiyongrenqun": {
		"title": "海苔的适用人群",
		"content": "\n海苔虽有种种好处，但中医认为紫菜味甘咸，性寒，能清热、化痰、利尿，夏天多吃紫菜有消暑热，补身体的作用，高血压患者、结核病人、脚气病人、肺热多痰的人适合多吃海苔，但脾胃虚寒、容易腹胀的人就不宜多吃。由于海苔在加工中经过调味，含有较多的盐分，因而需要控盐的人也要适当克制调味海苔的食用量，可以适当吃些没有调味的紫菜片。\n干海苔的盐分和味精含量很高，不宜长期连续食用，一次最好不要超过1两。尤其是幼儿和患有高血压的人群，不要常吃，吃完后要及时喝水。\n"
	}
}
