{
	"name": "花蟹",
	"jieshao": {
		"title": "花蟹的介绍",
		"content": "头胸甲宽约为长的2倍，梭形，表面具粗糙的颗粒，雌性的颗粒较雄性显著；前额具4齿，中间1对额齿较短小，成体的较尖锐，幼体的较圆钝；前侧缘具9尖齿，末齿比前面各齿大得多，向两侧突出。螯脚左右大小不同，瘦长，雄性螯脚长度约等于头胸甲长的4倍，表面具花纹。"
	},
	"foodvalue": {
		"title": "花蟹的营养成分(营养素含量/每100克)",
		"data": [
			{
				"name": "营养素",
				"value": "含量(每100克)"
			},
			{
				"name": "硒(微克)",
				"value": "82.65"
			},
			{
				"name": "钠(毫克)",
				"value": "260.00"
			},
			{
				"name": "磷(毫克)",
				"value": "142.00"
			},
			{
				"name": "钾(毫克)",
				"value": "232.00"
			},
			{
				"name": "锰(毫克)",
				"value": "0.18"
			},
			{
				"name": "铜(毫克)",
				"value": "1.67"
			},
			{
				"name": "锌(毫克)",
				"value": "3.32"
			},
			{
				"name": "铁(毫克)",
				"value": "1.60"
			},
			{
				"name": "钙(毫克)",
				"value": "208.00"
			},
			{
				"name": "镁(毫克)",
				"value": "47.00"
			},
			{
				"name": "胆固醇(毫克)",
				"value": "125.00"
			},
			{
				"name": "烟酸(毫克)",
				"value": "2.50"
			},
			{
				"name": "核黄素(毫克)",
				"value": "0.10"
			},
			{
				"name": "硫胺素(毫克)",
				"value": "0.01"
			},
			{
				"name": "胡罗卜素(微克)",
				"value": "一"
			},
			{
				"name": "维生素E(毫克)",
				"value": "2.99"
			},
			{
				"name": "维生素C(毫克)",
				"value": "一"
			},
			{
				"name": "维生素A(微克)",
				"value": "30.00"
			},
			{
				"name": "蛋白质(克)",
				"value": "13.80"
			},
			{
				"name": "脂肪(克)",
				"value": "2.30"
			},
			{
				"name": "碳水化合物(克)",
				"value": "4.70"
			},
			{
				"name": "热量(大卡)",
				"value": "95.00"
			},
			{
				"name": "",
				"value": ""
			},
			{
				"name": "",
				"value": ""
			},
			{
				"name": "",
				"value": ""
			}
		]
	},
	"gongxiao": {
		"title": "花蟹的功效",
		"content": "性味：咸、寒、有小毒。归经：入肝、胃。养筋益气、理胃消食，散诸热，通经络，解结散血。对于淤血、黄疸、腰腿酸痛和风湿性关节炎等有一定的食疗效果。"
	},
	"yingyangjiazhi": {
		"title": "花蟹的营养价值",
		"content": "螃蟹含有丰富的蛋白质及微量元素，对身体有很好的滋补作用。螃蟹还有抗结核作用，吃蟹对结核病的康复大有补益。"
	},
	"shiyongxiaoguo": {
		"title": "花蟹的",
		"content": ""
	},
	"shiyongrenqun": {
		"title": "花蟹的适用人群",
		"content": "适宜跌打损伤、筋断骨碎、瘀血肿痛、产妇胎盘残留、孕妇临产阵缩无力、胎儿迟迟不下者食用，尤以蟹爪为好。"
	}
}
