{
	"name": "苋菜",
	"jieshao": {
		"title": "苋菜的介绍",
		"content": "\n为苋科一年生草木植物苋的茎叶，其嫩苗和嫩茎叶可食用。\n苋菜原本是一种野菜，近几年才摆上餐桌。有的地区把苋菜称为“长寿菜”。因其富含多种人体需要的维生素和矿物质，且都是易被人体吸收的重要物质。同时对于增强体质，提高机体的免疫力，促进儿童生长发育，加快骨折愈合，减肥排毒，防止便秘和贫血患者、临产孕妇的绝佳美食。\n"
	},
	"foodvalue": {
		"title": "苋菜的营养成分(营养素含量/每100克)",
		"data": [
			{
				"name": "营养素",
				"value": "含量(每100克)"
			},
			{
				"name": "热量(大卡)",
				"value": "293.00"
			},
			{
				"name": "碳水化合物(克)",
				"value": "71.20"
			},
			{
				"name": "脂肪(克)",
				"value": "1.30"
			},
			{
				"name": "蛋白质(克)",
				"value": "7.40"
			},
			{
				"name": "纤维素(克)",
				"value": "8.20"
			},
			{
				"name": "维生素A(微克)",
				"value": "472.00"
			},
			{
				"name": "维生素C(毫克)",
				"value": "75.00"
			},
			{
				"name": "维生素E(毫克)",
				"value": "22.15"
			},
			{
				"name": "胡罗卜素(微克)",
				"value": "2830.00"
			},
			{
				"name": "硫胺素(毫克)",
				"value": "0.17"
			},
			{
				"name": "核黄素(毫克)",
				"value": "0.28"
			},
			{
				"name": "烟酸(毫克)",
				"value": "6.00"
			},
			{
				"name": "胆固醇(毫克)",
				"value": "一"
			},
			{
				"name": "镁(毫克)",
				"value": "269.00"
			},
			{
				"name": "钙(毫克)",
				"value": "1723.00"
			},
			{
				"name": "铁(毫克)",
				"value": "22.30"
			},
			{
				"name": "锌(毫克)",
				"value": "1.71"
			},
			{
				"name": "铜(毫克)",
				"value": "1.65"
			},
			{
				"name": "锰(毫克)",
				"value": "2.46"
			},
			{
				"name": "钾(毫克)",
				"value": "1031.00"
			},
			{
				"name": "磷(毫克)",
				"value": "151.00"
			},
			{
				"name": "钠(毫克)",
				"value": "1217.50"
			},
			{
				"name": "硒(微克)",
				"value": "14.15"
			},
			{
				"name": "",
				"value": ""
			},
			{
				"name": "",
				"value": ""
			}
		]
	},
	"gongxiao": {
		"title": "苋菜的功效",
		"content": "清热利湿，凉血止血，止痢"
	},
	"yingyangjiazhi": {
		"title": "苋菜的营养价值",
		"content": "\n苋菜叶富含易被人体吸收的钙质，对牙齿和骨骼的生长可起到促进作用，并能维持正常的心肌活动，防止肌内痉挛。同时含有丰富的铁、钙和维生素K，可以促进凝血，增加血红蛋白含量并提高携氧能力，促进造血等功能。\n苋菜还是减肥餐桌上的主角，常食可以减肥轻身，促进排毒，防止便秘。 同时常吃苋菜可增强体质，苋菜中富含蛋白质、脂肪。糖类及多种维生素和矿物质，其所含的蛋白质比牛奶更能充分被人体吸收，所含胡萝卜素比茄果类高，可为人体提供丰富的营养物质，有利于强身健体，提高机体的免疫力，有“长寿菜”之称。\n促进儿童生长发育，苋莱中铁、钙的含量比菠菜高，为鲜蔬菜中的佼佼者。更重要的是，苋莱中不含草酸，所含钙、铁进人人体后很容易被吸收利用。因此，苋菜能促进小儿的生长发育，对骨折的愈合具有一定的食疗价值。\n同时也适宜于妇女和老年人食用，对牙齿和骨骼生长可起到促进作用；苋菜对于维持正常心肌活动，促进凝血也大有裨益，这是因为它所含丰富的铁可以合成红细胞中的血红蛋白，有造血和携带氧气的功能，最宜贫血患者食用。因此我国民间常将苋菜与马齿苋，一起视为骨折之人和临产孕妇的最佳食蔬。 \n"
	},
	"shiyongxiaoguo": {
		"title": "苋菜的使用效果",
		"content": "\n苋菜性凉、味微甘，人肺、大肠经；\n有清热、解毒、利尿、通利大便等功效。\n"
	},
	"shiyongrenqun": {
		"title": "苋菜的适用人群",
		"content": "\n一般人群均可食用。\n1. 适合老年人、幼儿、妇女、减肥者食用。在夏季食用红苋菜对于清热解毒，治疗肠炎痢疾以及大便干结和小便赤涩有显著作用。\n2. 脾胃虚寒者忌食；平素胃肠有寒气、易腹泻的人也不宜多食。\n"
	}
}
