{
	"name": "蛏子",
	"jieshao": {
		"title": "蛏子的介绍",
		"content": "\n      蛏子，学名缢蛏，属软体动物系，真瓣鳃纲，真瓣鳃目、竹蛏科。贝壳脆而薄，呈长扁方型，自壳顶腹缘，有一道斜行的凹沟，故名缢蛏。\n蛏生活在浅海泥沙中,有左右相等的两个贝壳,壳质脆薄,呈长方形,表面常生长一层浅绿色的薄皮。蛏肉味道鲜美,是比较普通的海产食品。\n    \n"
	},
	"foodvalue": {
		"title": "蛏子的营养成分(营养素含量/每100克)",
		"data": [
			{
				"name": "食部",
				"value": "57%"
			},
			{
				"name": "水分(克)",
				"value": "88.4"
			},
			{
				"name": "能量(千卡)",
				"value": "40"
			},
			{
				"name": "蛋白质(克)",
				"value": "7.3"
			},
			{
				"name": "脂肪(克)",
				"value": "0.3"
			},
			{
				"name": "碳水化合物(克)",
				"value": "2.1"
			},
			{
				"name": "不溶性纤维(克)",
				"value": " — "
			},
			{
				"name": "胆固醇(毫克)",
				"value": "131"
			},
			{
				"name": "灰分(克)",
				"value": "1.9"
			},
			{
				"name": "维生素A(微克RE)",
				"value": "59"
			},
			{
				"name": "胡萝卜素(微克)",
				"value": " — "
			},
			{
				"name": "视黄醇(微克)",
				"value": "59"
			},
			{
				"name": "硫胺素(毫克)",
				"value": "0.02"
			},
			{
				"name": "核黄素(毫克)",
				"value": "0.12"
			},
			{
				"name": "尼克酸(毫克)",
				"value": "1.2"
			},
			{
				"name": "维生素C(毫克)",
				"value": " — "
			},
			{
				"name": "维生素E(毫克)",
				"value": "0.59"
			},
			{
				"name": "钙(毫克)",
				"value": "134"
			},
			{
				"name": "磷(毫克)",
				"value": "114"
			},
			{
				"name": "钾(毫克)",
				"value": "140"
			},
			{
				"name": "钠(毫克)",
				"value": "175.9"
			},
			{
				"name": "镁(毫克)",
				"value": "35"
			},
			{
				"name": "铁(毫克)",
				"value": "33.6"
			},
			{
				"name": "锌(毫克)",
				"value": "2.01"
			},
			{
				"name": "硒(微克)",
				"value": "55.14"
			},
			{
				"name": "铜(毫克)",
				"value": "0.38"
			},
			{
				"name": "锰(毫克)",
				"value": "11.93"
			},
			{
				"name": "酒精(毫升)%",
				"value": " — "
			},
			{
				"name": "酒精(克)",
				"value": " — "
			},
			{
				"name": "",
				"value": ""
			},
			{
				"name": "",
				"value": ""
			},
			{
				"name": "",
				"value": ""
			}
		]
	},
	"gongxiao": {
		"title": "蛏子的功效",
		"content": "\n蛏肉味甘咸、性寒，入心、肝、肾经；具有补阴，清热，除烦，解酒毒等功效。对产后虚损，烦热口渴，湿热水肿，痢疾具有一定治疗效果。\n"
	},
	"yingyangjiazhi": {
		"title": "蛏子的营养价值",
		"content": "\n蛏肉含丰富蛋白质、钙、铁、硒、维生素A等营养元素，滋味鲜美，营养价值高，具有补虚的功能。      \n"
	},
	"shiyongxiaoguo": {
		"title": "蛏子的使用效果",
		"content": "\n蛏肉味甘咸、性寒，入心、肝、肾经；\n具有补阴，清热，除烦，解酒毒等功效；\n对产后虚损，烦热口渴，湿热水肿，痢疾，醉酒等有一定治疗作用。\n"
	},
	"shiyongrenqun": {
		"title": "蛏子的适用人群",
		"content": "\n一般人都可食用。适宜产后虚损、烦热口渴、湿热水肿、痢疾、醉酒等人群。\n"
	}
}
