[
	{
		"name": "罗汉果",
		"url": "http://i1.douguo.net//upload/shicai/1446113762.jpg"
	},
	{
		"name": "川贝",
		"url": "http://i1.douguo.net//upload/shicai/1446100887.jpg"
	},
	{
		"name": "首乌",
		"url": "http://i1.douguo.net//upload/shicai/1446102383.jpg"
	},
	{
		"name": "人参",
		"url": "http://i1.douguo.net//upload/shicai/1446026737.jpg"
	},
	{
		"name": "荷叶",
		"url": "http://i1.douguo.net//upload/shicai/1446106769.jpg"
	},
	{
		"name": "阿胶",
		"url": "http://i1.douguo.net//upload/shicai/1446099008.jpg"
	},
	{
		"name": "冬虫夏草",
		"url": "http://i1.douguo.net//upload/shicai/1446101219.jpg"
	},
	{
		"name": "陈皮",
		"url": "http://i1.douguo.net//upload/shicai/1446100725.jpg"
	},
	{
		"name": "白芷",
		"url": "http://i1.douguo.net//upload/shicai/1446100191.jpg"
	},
	{
		"name": "肉桂",
		"url": "http://i1.douguo.net//upload/shicai/1446026752.jpg"
	}
]